robopid/__init__.py
robopid/pid.py
robo_pid-0.2.6.dist-info/LICENSE
robo_pid-0.2.6.dist-info/METADATA
robo_pid-0.2.6.dist-info/WHEEL
robo_pid-0.2.6.dist-info/top_level.txt
robo_pid-0.2.6.dist-info/RECORD
