Metadata-Version: 2.1
Name: robo-pid
Version: 0.2.6
Summary: PID Controller For Mobile Robotic Regulators
Home-page: https://github.com/mkner/robo-pid
Author: Mike Knerr
License: BSD
Keywords: PID,controllers,regulators,discrete time systems,mobile robotics,robotics
Platform: UNKNOWN
Classifier: Programming Language :: Python :: 3
Classifier: License :: OSI Approved :: BSD License
Classifier: Operating System :: OS Independent
License-File: LICENSE
Requires-Dist: robo-base (>=0.1.4)
